{"wfHrv_Updates_Recs":[{"RecId":2664,"Area":"Duck Creek CA","Season":"2019-2020","Week":1,"Report_Date":"2019-11-09T00:00:00","Duck_Pop":13237,"Goose_Pop":null,"Duck_Harv":153,"CG_Harv":0,"SBG_Harv":0,"WFG_Harv":0,"Watfowl_Harv":153,"Num_Hunters":52,"Birds_Per_Hunt":2.94,"Ducks_Per_Hunt":2.94,"Blind_Vac":0,"Wade_Vac":0,"Total_Pos":20,"PL_Avail":13,"PL_Draw":63,"Comments":null,"Area_ID":5001},{"RecId":2668,"Area":"Duck Creek CA","Season":"2019-2020","Week":1,"Report_Date":"2019-11-10T00:00:00","Duck_Pop":13237,"Goose_Pop":null,"Duck_Harv":80,"CG_Harv":0,"SBG_Harv":0,"WFG_Harv":0,"Watfowl_Harv":80,"Num_Hunters":56,"Birds_Per_Hunt":1.43,"Ducks_Per_Hunt":1.43,"Blind_Vac":0,"Wade_Vac":0,"Total_Pos":20,"PL_Avail":13,"PL_Draw":49,"Comments":null,"Area_ID":5001},{"RecId":2688,"Area":"Duck Creek CA","Season":"2019-2020","Week":2,"Report_Date":"2019-11-11T00:00:00","Duck_Pop":23855,"Goose_Pop":64,"Duck_Harv":95,"CG_Harv":0,"SBG_Harv":1,"WFG_Harv":0,"Watfowl_Harv":96,"Num_Hunters":51,"Birds_Per_Hunt":1.88,"Ducks_Per_Hunt":1.86,"Blind_Vac":0,"Wade_Vac":0,"Total_Pos":19,"PL_Avail":12,"PL_Draw":42,"Comments":null,"Area_ID":5001},{"RecId":2689,"Area":"Duck Creek CA","Season":"2019-2020","Week":2,"Report_Date":"2019-11-12T00:00:00","Duck_Pop":23855,"Goose_Pop":64,"Duck_Harv":82,"CG_Harv":0,"SBG_Harv":0,"WFG_Harv":0,"Watfowl_Harv":82,"Num_Hunters":44,"Birds_Per_Hunt":1.86,"Ducks_Per_Hunt":1.86,"Blind_Vac":0,"Wade_Vac":1,"Total_Pos":18,"PL_Avail":15,"PL_Draw":19,"Comments":null,"Area_ID":5001},{"RecId":2690,"Area":"Duck Creek CA","Season":"2019-2020","Week":2,"Report_Date":"2019-11-13T00:00:00","Duck_Pop":7988,"Goose_Pop":null,"Duck_Harv":63,"CG_Harv":0,"SBG_Harv":0,"WFG_Harv":0,"Watfowl_Harv":53,"Num_Hunters":40,"Birds_Per_Hunt":1.32,"Ducks_Per_Hunt":1.75,"Blind_Vac":0,"Wade_Vac":3,"Total_Pos":20,"PL_Avail":16,"PL_Draw":19,"Comments":null,"Area_ID":5001},{"RecId":2766,"Area":"Duck Creek CA","Season":"2019-2020","Week":2,"Report_Date":"2019-11-14T00:00:00","Duck_Pop":7988,"Goose_Pop":null,"Duck_Harv":56,"CG_Harv":0,"SBG_Harv":0,"WFG_Harv":1,"Watfowl_Harv":57,"Num_Hunters":37,"Birds_Per_Hunt":1.54,"Ducks_Per_Hunt":1.51,"Blind_Vac":0,"Wade_Vac":0,"Total_Pos":18,"PL_Avail":14,"PL_Draw":18,"Comments":null,"Area_ID":5001},{"RecId":2767,"Area":"Duck Creek CA","Season":"2019-2020","Week":2,"Report_Date":"2019-11-15T00:00:00","Duck_Pop":7988,"Goose_Pop":null,"Duck_Harv":66,"CG_Harv":0,"SBG_Harv":0,"WFG_Harv":0,"Watfowl_Harv":66,"Num_Hunters":44,"Birds_Per_Hunt":1.50,"Ducks_Per_Hunt":1.50,"Blind_Vac":0,"Wade_Vac":0,"Total_Pos":18,"PL_Avail":12,"PL_Draw":22,"Comments":null,"Area_ID":5001},{"RecId":2907,"Area":"Duck Creek CA","Season":"2019-2020","Week":3,"Report_Date":"2019-11-21T00:00:00","Duck_Pop":7027,"Goose_Pop":20,"Duck_Harv":129,"CG_Harv":0,"SBG_Harv":0,"WFG_Harv":0,"Watfowl_Harv":129,"Num_Hunters":57,"Birds_Per_Hunt":2.26,"Ducks_Per_Hunt":2.26,"Blind_Vac":0,"Wade_Vac":3,"Total_Pos":34,"PL_Avail":27,"PL_Draw":29,"Comments":null,"Area_ID":5001},{"RecId":2908,"Area":"Duck Creek CA","Season":"2019-2020","Week":3,"Report_Date":"2019-11-22T00:00:00","Duck_Pop":7027,"Goose_Pop":20,"Duck_Harv":104,"CG_Harv":0,"SBG_Harv":0,"WFG_Harv":0,"Watfowl_Harv":104,"Num_Hunters":61,"Birds_Per_Hunt":1.70,"Ducks_Per_Hunt":1.70,"Blind_Vac":1,"Wade_Vac":4,"Total_Pos":34,"PL_Avail":27,"PL_Draw":35,"Comments":null,"Area_ID":5001},{"RecId":2909,"Area":"Duck Creek CA","Season":"2019-2020","Week":3,"Report_Date":"2019-11-23T00:00:00","Duck_Pop":7027,"Goose_Pop":20,"Duck_Harv":91,"CG_Harv":0,"SBG_Harv":0,"WFG_Harv":0,"Watfowl_Harv":91,"Num_Hunters":101,"Birds_Per_Hunt":0.90,"Ducks_Per_Hunt":0.90,"Blind_Vac":0,"Wade_Vac":0,"Total_Pos":37,"PL_Avail":30,"PL_Draw":48,"Comments":null,"Area_ID":5001},{"RecId":2910,"Area":"Duck Creek CA","Season":"2019-2020","Week":3,"Report_Date":"2019-11-24T00:00:00","Duck_Pop":7027,"Goose_Pop":20,"Duck_Harv":53,"CG_Harv":0,"SBG_Harv":0,"WFG_Harv":0,"Watfowl_Harv":53,"Num_Hunters":91,"Birds_Per_Hunt":0.58,"Ducks_Per_Hunt":0.58,"Blind_Vac":0,"Wade_Vac":2,"Total_Pos":37,"PL_Avail":30,"PL_Draw":48,"Comments":null,"Area_ID":5001},{"RecId":2911,"Area":"Duck Creek CA","Season":"2019-2020","Week":4,"Report_Date":"2019-11-25T00:00:00","Duck_Pop":5802,"Goose_Pop":0,"Duck_Harv":44,"CG_Harv":0,"SBG_Harv":0,"WFG_Harv":1,"Watfowl_Harv":45,"Num_Hunters":61,"Birds_Per_Hunt":0.74,"Ducks_Per_Hunt":0.72,"Blind_Vac":0,"Wade_Vac":9,"Total_Pos":35,"PL_Avail":26,"PL_Draw":20,"Comments":null,"Area_ID":5001},{"RecId":2948,"Area":"Duck Creek CA","Season":"2019-2020","Week":4,"Report_Date":"2019-11-26T00:00:00","Duck_Pop":5802,"Goose_Pop":0,"Duck_Harv":31,"CG_Harv":1,"SBG_Harv":0,"WFG_Harv":1,"Watfowl_Harv":33,"Num_Hunters":46,"Birds_Per_Hunt":0.72,"Ducks_Per_Hunt":0.67,"Blind_Vac":3,"Wade_Vac":13,"Total_Pos":38,"PL_Avail":36,"PL_Draw":22,"Comments":null,"Area_ID":5001},{"RecId":2949,"Area":"Duck Creek CA","Season":"2019-2020","Week":4,"Report_Date":"2019-11-27T00:00:00","Duck_Pop":5802,"Goose_Pop":0,"Duck_Harv":48,"CG_Harv":0,"SBG_Harv":0,"WFG_Harv":0,"Watfowl_Harv":48,"Num_Hunters":71,"Birds_Per_Hunt":0.68,"Ducks_Per_Hunt":0.68,"Blind_Vac":0,"Wade_Vac":7,"Total_Pos":39,"PL_Avail":33,"PL_Draw":32,"Comments":null,"Area_ID":5001},{"RecId":2950,"Area":"Duck Creek CA","Season":"2019-2020","Week":4,"Report_Date":"2019-11-28T00:00:00","Duck_Pop":5802,"Goose_Pop":0,"Duck_Harv":150,"CG_Harv":0,"SBG_Harv":0,"WFG_Harv":0,"Watfowl_Harv":150,"Num_Hunters":106,"Birds_Per_Hunt":1.42,"Ducks_Per_Hunt":1.42,"Blind_Vac":0,"Wade_Vac":3,"Total_Pos":45,"PL_Avail":36,"PL_Draw":56,"Comments":null,"Area_ID":5001},{"RecId":2951,"Area":"Duck Creek CA","Season":"2019-2020","Week":4,"Report_Date":"2019-11-29T00:00:00","Duck_Pop":5802,"Goose_Pop":0,"Duck_Harv":110,"CG_Harv":0,"SBG_Harv":0,"WFG_Harv":0,"Watfowl_Harv":110,"Num_Hunters":91,"Birds_Per_Hunt":1.21,"Ducks_Per_Hunt":1.21,"Blind_Vac":2,"Wade_Vac":11,"Total_Pos":48,"PL_Avail":48,"PL_Draw":0,"Comments":null,"Area_ID":5001},{"RecId":2952,"Area":"Duck Creek CA","Season":"2019-2020","Week":4,"Report_Date":"2019-11-30T00:00:00","Duck_Pop":5802,"Goose_Pop":0,"Duck_Harv":86,"CG_Harv":1,"SBG_Harv":0,"WFG_Harv":0,"Watfowl_Harv":87,"Num_Hunters":114,"Birds_Per_Hunt":0.76,"Ducks_Per_Hunt":0.75,"Blind_Vac":0,"Wade_Vac":13,"Total_Pos":54,"PL_Avail":47,"PL_Draw":50,"Comments":null,"Area_ID":5001},{"RecId":2973,"Area":"Duck Creek CA","Season":"2019-2020","Week":4,"Report_Date":"2019-12-01T00:00:00","Duck_Pop":5802,"Goose_Pop":0,"Duck_Harv":134,"CG_Harv":0,"SBG_Harv":0,"WFG_Harv":0,"Watfowl_Harv":134,"Num_Hunters":105,"Birds_Per_Hunt":1.28,"Ducks_Per_Hunt":1.28,"Blind_Vac":0,"Wade_Vac":9,"Total_Pos":48,"PL_Avail":40,"PL_Draw":67,"Comments":null,"Area_ID":5001},{"RecId":3102,"Area":"Duck Creek CA","Season":"2019-2020","Week":5,"Report_Date":"2019-12-02T00:00:00","Duck_Pop":6920,"Goose_Pop":30,"Duck_Harv":88,"CG_Harv":0,"SBG_Harv":0,"WFG_Harv":0,"Watfowl_Harv":88,"Num_Hunters":65,"Birds_Per_Hunt":1.35,"Ducks_Per_Hunt":1.35,"Blind_Vac":4,"Wade_Vac":15,"Total_Pos":48,"PL_Avail":39,"PL_Draw":34,"Comments":null,"Area_ID":5001},{"RecId":3103,"Area":"Duck Creek CA","Season":"2019-2020","Week":5,"Report_Date":"2019-12-03T00:00:00","Duck_Pop":6920,"Goose_Pop":30,"Duck_Harv":118,"CG_Harv":0,"SBG_Harv":0,"WFG_Harv":0,"Watfowl_Harv":118,"Num_Hunters":88,"Birds_Per_Hunt":1.34,"Ducks_Per_Hunt":1.34,"Blind_Vac":5,"Wade_Vac":11,"Total_Pos":53,"PL_Avail":47,"PL_Draw":42,"Comments":null,"Area_ID":5001},{"RecId":3104,"Area":"Duck Creek CA","Season":"2019-2020","Week":5,"Report_Date":"2019-12-04T00:00:00","Duck_Pop":6920,"Goose_Pop":30,"Duck_Harv":168,"CG_Harv":0,"SBG_Harv":0,"WFG_Harv":0,"Watfowl_Harv":168,"Num_Hunters":92,"Birds_Per_Hunt":1.83,"Ducks_Per_Hunt":1.83,"Blind_Vac":5,"Wade_Vac":16,"Total_Pos":49,"PL_Avail":40,"PL_Draw":48,"Comments":null,"Area_ID":5001},{"RecId":3145,"Area":"Duck Creek CA","Season":"2019-2020","Week":5,"Report_Date":"2019-12-05T00:00:00","Duck_Pop":6920,"Goose_Pop":30,"Duck_Harv":83,"CG_Harv":0,"SBG_Harv":0,"WFG_Harv":0,"Watfowl_Harv":83,"Num_Hunters":62,"Birds_Per_Hunt":1.34,"Ducks_Per_Hunt":1.34,"Blind_Vac":6,"Wade_Vac":23,"Total_Pos":59,"PL_Avail":53,"PL_Draw":42,"Comments":null,"Area_ID":5001},{"RecId":3146,"Area":"Duck Creek CA","Season":"2019-2020","Week":5,"Report_Date":"2019-12-06T00:00:00","Duck_Pop":6920,"Goose_Pop":30,"Duck_Harv":96,"CG_Harv":0,"SBG_Harv":0,"WFG_Harv":0,"Watfowl_Harv":96,"Num_Hunters":70,"Birds_Per_Hunt":1.37,"Ducks_Per_Hunt":1.37,"Blind_Vac":8,"Wade_Vac":18,"Total_Pos":59,"PL_Avail":49,"PL_Draw":62,"Comments":null,"Area_ID":5001},{"RecId":3171,"Area":"Duck Creek CA","Season":"2019-2020","Week":5,"Report_Date":"2019-12-07T00:00:00","Duck_Pop":6920,"Goose_Pop":30,"Duck_Harv":125,"CG_Harv":2,"SBG_Harv":0,"WFG_Harv":0,"Watfowl_Harv":127,"Num_Hunters":139,"Birds_Per_Hunt":0.91,"Ducks_Per_Hunt":0.90,"Blind_Vac":4,"Wade_Vac":9,"Total_Pos":67,"PL_Avail":60,"PL_Draw":116,"Comments":null,"Area_ID":5001},{"RecId":3172,"Area":"Duck Creek CA","Season":"2019-2020","Week":5,"Report_Date":"2019-12-08T00:00:00","Duck_Pop":6920,"Goose_Pop":30,"Duck_Harv":268,"CG_Harv":0,"SBG_Harv":0,"WFG_Harv":0,"Watfowl_Harv":268,"Num_Hunters":124,"Birds_Per_Hunt":2.16,"Ducks_Per_Hunt":2.16,"Blind_Vac":10,"Wade_Vac":9,"Total_Pos":67,"PL_Avail":58,"PL_Draw":60,"Comments":null,"Area_ID":5001},{"RecId":3224,"Area":"Duck Creek CA","Season":"2019-2020","Week":6,"Report_Date":"2019-12-09T00:00:00","Duck_Pop":6404,"Goose_Pop":null,"Duck_Harv":177,"CG_Harv":0,"SBG_Harv":0,"WFG_Harv":0,"Watfowl_Harv":177,"Num_Hunters":76,"Birds_Per_Hunt":2.33,"Ducks_Per_Hunt":2.33,"Blind_Vac":12,"Wade_Vac":20,"Total_Pos":67,"PL_Avail":61,"PL_Draw":39,"Comments":null,"Area_ID":5001},{"RecId":3229,"Area":"Duck Creek CA","Season":"2019-2020","Week":6,"Report_Date":"2019-12-10T00:00:00","Duck_Pop":6404,"Goose_Pop":null,"Duck_Harv":172,"CG_Harv":0,"SBG_Harv":0,"WFG_Harv":0,"Watfowl_Harv":172,"Num_Hunters":100,"Birds_Per_Hunt":1.72,"Ducks_Per_Hunt":1.72,"Blind_Vac":9,"Wade_Vac":20,"Total_Pos":67,"PL_Avail":57,"PL_Draw":57,"Comments":null,"Area_ID":5001},{"RecId":3226,"Area":"Duck Creek CA","Season":"2019-2020","Week":6,"Report_Date":"2019-12-11T00:00:00","Duck_Pop":6404,"Goose_Pop":null,"Duck_Harv":160,"CG_Harv":1,"SBG_Harv":0,"WFG_Harv":0,"Watfowl_Harv":161,"Num_Hunters":110,"Birds_Per_Hunt":1.46,"Ducks_Per_Hunt":1.45,"Blind_Vac":11,"Wade_Vac":8,"Total_Pos":67,"PL_Avail":56,"PL_Draw":56,"Comments":null,"Area_ID":5001},{"RecId":3277,"Area":"Duck Creek CA","Season":"2019-2020","Week":6,"Report_Date":"2019-12-12T00:00:00","Duck_Pop":6404,"Goose_Pop":null,"Duck_Harv":109,"CG_Harv":0,"SBG_Harv":0,"WFG_Harv":0,"Watfowl_Harv":109,"Num_Hunters":91,"Birds_Per_Hunt":1.20,"Ducks_Per_Hunt":1.20,"Blind_Vac":10,"Wade_Vac":15,"Total_Pos":60,"PL_Avail":49,"PL_Draw":44,"Comments":null,"Area_ID":5001},{"RecId":3278,"Area":"Duck Creek CA","Season":"2019-2020","Week":6,"Report_Date":"2019-12-13T00:00:00","Duck_Pop":6404,"Goose_Pop":null,"Duck_Harv":123,"CG_Harv":0,"SBG_Harv":0,"WFG_Harv":0,"Watfowl_Harv":123,"Num_Hunters":102,"Birds_Per_Hunt":1.21,"Ducks_Per_Hunt":1.21,"Blind_Vac":6,"Wade_Vac":13,"Total_Pos":60,"PL_Avail":50,"PL_Draw":63,"Comments":null,"Area_ID":5001},{"RecId":3279,"Area":"Duck Creek CA","Season":"2019-2020","Week":6,"Report_Date":"2019-12-14T00:00:00","Duck_Pop":6404,"Goose_Pop":null,"Duck_Harv":232,"CG_Harv":0,"SBG_Harv":0,"WFG_Harv":0,"Watfowl_Harv":232,"Num_Hunters":161,"Birds_Per_Hunt":1.44,"Ducks_Per_Hunt":1.44,"Blind_Vac":1,"Wade_Vac":14,"Total_Pos":60,"PL_Avail":52,"PL_Draw":102,"Comments":null,"Area_ID":5001},{"RecId":3280,"Area":"Duck Creek CA","Season":"2019-2020","Week":6,"Report_Date":"2019-12-15T00:00:00","Duck_Pop":6404,"Goose_Pop":null,"Duck_Harv":199,"CG_Harv":0,"SBG_Harv":0,"WFG_Harv":0,"Watfowl_Harv":199,"Num_Hunters":151,"Birds_Per_Hunt":1.32,"Ducks_Per_Hunt":1.32,"Blind_Vac":7,"Wade_Vac":12,"Total_Pos":60,"PL_Avail":45,"PL_Draw":92,"Comments":null,"Area_ID":5001},{"RecId":3316,"Area":"Duck Creek CA","Season":"2019-2020","Week":7,"Report_Date":"2019-12-16T00:00:00","Duck_Pop":9467,"Goose_Pop":0,"Duck_Harv":179,"CG_Harv":0,"SBG_Harv":0,"WFG_Harv":0,"Watfowl_Harv":179,"Num_Hunters":97,"Birds_Per_Hunt":1.85,"Ducks_Per_Hunt":1.85,"Blind_Vac":8,"Wade_Vac":17,"Total_Pos":64,"PL_Avail":57,"PL_Draw":52,"Comments":null,"Area_ID":5001},{"RecId":3317,"Area":"Duck Creek CA","Season":"2019-2020","Week":7,"Report_Date":"2019-12-17T00:00:00","Duck_Pop":9467,"Goose_Pop":0,"Duck_Harv":178,"CG_Harv":0,"SBG_Harv":0,"WFG_Harv":0,"Watfowl_Harv":178,"Num_Hunters":100,"Birds_Per_Hunt":1.78,"Ducks_Per_Hunt":1.78,"Blind_Vac":9,"Wade_Vac":19,"Total_Pos":72,"PL_Avail":67,"PL_Draw":59,"Comments":null,"Area_ID":5001},{"RecId":3318,"Area":"Duck Creek CA","Season":"2019-2020","Week":7,"Report_Date":"2019-12-18T00:00:00","Duck_Pop":9467,"Goose_Pop":0,"Duck_Harv":84,"CG_Harv":0,"SBG_Harv":0,"WFG_Harv":0,"Watfowl_Harv":84,"Num_Hunters":113,"Birds_Per_Hunt":0.74,"Ducks_Per_Hunt":0.74,"Blind_Vac":9,"Wade_Vac":23,"Total_Pos":81,"PL_Avail":71,"PL_Draw":59,"Comments":null,"Area_ID":5001},{"RecId":3360,"Area":"Duck Creek CA","Season":"2019-2020","Week":7,"Report_Date":"2019-12-19T00:00:00","Duck_Pop":9467,"Goose_Pop":0,"Duck_Harv":69,"CG_Harv":0,"SBG_Harv":0,"WFG_Harv":0,"Watfowl_Harv":69,"Num_Hunters":83,"Birds_Per_Hunt":0.83,"Ducks_Per_Hunt":0.83,"Blind_Vac":13,"Wade_Vac":18,"Total_Pos":63,"PL_Avail":57,"PL_Draw":30,"Comments":null,"Area_ID":5001},{"RecId":3361,"Area":"Duck Creek CA","Season":"2019-2020","Week":7,"Report_Date":"2019-12-20T00:00:00","Duck_Pop":9467,"Goose_Pop":0,"Duck_Harv":94,"CG_Harv":0,"SBG_Harv":0,"WFG_Harv":0,"Watfowl_Harv":94,"Num_Hunters":96,"Birds_Per_Hunt":0.98,"Ducks_Per_Hunt":0.98,"Blind_Vac":10,"Wade_Vac":13,"Total_Pos":59,"PL_Avail":49,"PL_Draw":31,"Comments":null,"Area_ID":5001},{"RecId":3362,"Area":"Duck Creek CA","Season":"2019-2020","Week":7,"Report_Date":"2019-12-21T00:00:00","Duck_Pop":9467,"Goose_Pop":0,"Duck_Harv":160,"CG_Harv":0,"SBG_Harv":0,"WFG_Harv":0,"Watfowl_Harv":160,"Num_Hunters":161,"Birds_Per_Hunt":0.99,"Ducks_Per_Hunt":0.99,"Blind_Vac":7,"Wade_Vac":11,"Total_Pos":82,"PL_Avail":74,"PL_Draw":67,"Comments":null,"Area_ID":5001},{"RecId":3363,"Area":"Duck Creek CA","Season":"2019-2020","Week":7,"Report_Date":"2019-12-22T00:00:00","Duck_Pop":9467,"Goose_Pop":0,"Duck_Harv":213,"CG_Harv":0,"SBG_Harv":0,"WFG_Harv":1,"Watfowl_Harv":214,"Num_Hunters":155,"Birds_Per_Hunt":1.38,"Ducks_Per_Hunt":1.37,"Blind_Vac":8,"Wade_Vac":11,"Total_Pos":81,"PL_Avail":71,"PL_Draw":67,"Comments":null,"Area_ID":5001},{"RecId":3391,"Area":"Duck Creek CA","Season":"2019-2020","Week":8,"Report_Date":"2019-12-23T00:00:00","Duck_Pop":16525,"Goose_Pop":null,"Duck_Harv":148,"CG_Harv":0,"SBG_Harv":0,"WFG_Harv":0,"Watfowl_Harv":148,"Num_Hunters":126,"Birds_Per_Hunt":1.17,"Ducks_Per_Hunt":1.17,"Blind_Vac":4,"Wade_Vac":10,"Total_Pos":65,"PL_Avail":55,"PL_Draw":62,"Comments":null,"Area_ID":5001},{"RecId":3392,"Area":"Duck Creek CA","Season":"2019-2020","Week":8,"Report_Date":"2019-12-24T00:00:00","Duck_Pop":16525,"Goose_Pop":null,"Duck_Harv":122,"CG_Harv":0,"SBG_Harv":0,"WFG_Harv":1,"Watfowl_Harv":123,"Num_Hunters":147,"Birds_Per_Hunt":0.84,"Ducks_Per_Hunt":0.83,"Blind_Vac":5,"Wade_Vac":10,"Total_Pos":72,"PL_Avail":62,"PL_Draw":84,"Comments":null,"Area_ID":5001},{"RecId":3414,"Area":"Duck Creek CA","Season":"2019-2020","Week":8,"Report_Date":"2019-12-26T00:00:00","Duck_Pop":16525,"Goose_Pop":null,"Duck_Harv":186,"CG_Harv":0,"SBG_Harv":0,"WFG_Harv":0,"Watfowl_Harv":186,"Num_Hunters":152,"Birds_Per_Hunt":1.22,"Ducks_Per_Hunt":1.22,"Blind_Vac":1,"Wade_Vac":6,"Total_Pos":65,"PL_Avail":53,"PL_Draw":60,"Comments":null,"Area_ID":5001},{"RecId":3415,"Area":"Duck Creek CA","Season":"2019-2020","Week":8,"Report_Date":"2019-12-27T00:00:00","Duck_Pop":16525,"Goose_Pop":null,"Duck_Harv":126,"CG_Harv":0,"SBG_Harv":0,"WFG_Harv":1,"Watfowl_Harv":127,"Num_Hunters":136,"Birds_Per_Hunt":0.93,"Ducks_Per_Hunt":0.93,"Blind_Vac":3,"Wade_Vac":11,"Total_Pos":68,"PL_Avail":59,"PL_Draw":58,"Comments":null,"Area_ID":5001},{"RecId":3416,"Area":"Duck Creek CA","Season":"2019-2020","Week":8,"Report_Date":"2019-12-28T00:00:00","Duck_Pop":16525,"Goose_Pop":null,"Duck_Harv":250,"CG_Harv":1,"SBG_Harv":0,"WFG_Harv":1,"Watfowl_Harv":252,"Num_Hunters":145,"Birds_Per_Hunt":1.74,"Ducks_Per_Hunt":1.72,"Blind_Vac":7,"Wade_Vac":13,"Total_Pos":83,"PL_Avail":15,"PL_Draw":7,"Comments":null,"Area_ID":5001},{"RecId":3417,"Area":"Duck Creek CA","Season":"2019-2020","Week":8,"Report_Date":"2019-12-29T00:00:00","Duck_Pop":16525,"Goose_Pop":null,"Duck_Harv":224,"CG_Harv":0,"SBG_Harv":0,"WFG_Harv":0,"Watfowl_Harv":224,"Num_Hunters":149,"Birds_Per_Hunt":1.50,"Ducks_Per_Hunt":1.50,"Blind_Vac":7,"Wade_Vac":16,"Total_Pos":87,"PL_Avail":76,"PL_Draw":70,"Comments":null,"Area_ID":5001},{"RecId":3450,"Area":"Duck Creek CA","Season":"2019-2020","Week":9,"Report_Date":"2019-12-30T00:00:00","Duck_Pop":15098,"Goose_Pop":null,"Duck_Harv":182,"CG_Harv":0,"SBG_Harv":0,"WFG_Harv":0,"Watfowl_Harv":182,"Num_Hunters":132,"Birds_Per_Hunt":1.38,"Ducks_Per_Hunt":1.38,"Blind_Vac":0,"Wade_Vac":10,"Total_Pos":68,"PL_Avail":58,"PL_Draw":72,"Comments":null,"Area_ID":5001},{"RecId":3451,"Area":"Duck Creek CA","Season":"2019-2020","Week":9,"Report_Date":"2019-12-31T00:00:00","Duck_Pop":15098,"Goose_Pop":null,"Duck_Harv":261,"CG_Harv":0,"SBG_Harv":0,"WFG_Harv":0,"Watfowl_Harv":261,"Num_Hunters":150,"Birds_Per_Hunt":1.74,"Ducks_Per_Hunt":1.74,"Blind_Vac":3,"Wade_Vac":8,"Total_Pos":73,"PL_Avail":63,"PL_Draw":69,"Comments":null,"Area_ID":5001},{"RecId":3452,"Area":"Duck Creek CA","Season":"2019-2020","Week":9,"Report_Date":"2020-01-01T00:00:00","Duck_Pop":15098,"Goose_Pop":null,"Duck_Harv":232,"CG_Harv":0,"SBG_Harv":0,"WFG_Harv":1,"Watfowl_Harv":233,"Num_Hunters":191,"Birds_Per_Hunt":1.22,"Ducks_Per_Hunt":1.21,"Blind_Vac":1,"Wade_Vac":7,"Total_Pos":85,"PL_Avail":80,"PL_Draw":98,"Comments":null,"Area_ID":5001},{"RecId":3481,"Area":"Duck Creek CA","Season":"2019-2020","Week":9,"Report_Date":"2020-01-02T00:00:00","Duck_Pop":15098,"Goose_Pop":null,"Duck_Harv":117,"CG_Harv":0,"SBG_Harv":0,"WFG_Harv":0,"Watfowl_Harv":117,"Num_Hunters":117,"Birds_Per_Hunt":1.00,"Ducks_Per_Hunt":1.00,"Blind_Vac":4,"Wade_Vac":14,"Total_Pos":68,"PL_Avail":56,"PL_Draw":68,"Comments":null,"Area_ID":5001},{"RecId":3482,"Area":"Duck Creek CA","Season":"2019-2020","Week":9,"Report_Date":"2020-01-03T00:00:00","Duck_Pop":15098,"Goose_Pop":null,"Duck_Harv":152,"CG_Harv":0,"SBG_Harv":0,"WFG_Harv":0,"Watfowl_Harv":152,"Num_Hunters":123,"Birds_Per_Hunt":1.24,"Ducks_Per_Hunt":1.24,"Blind_Vac":8,"Wade_Vac":10,"Total_Pos":68,"PL_Avail":62,"PL_Draw":53,"Comments":null,"Area_ID":5001},{"RecId":3483,"Area":"Duck Creek CA","Season":"2019-2020","Week":9,"Report_Date":"2020-01-04T00:00:00","Duck_Pop":15098,"Goose_Pop":null,"Duck_Harv":143,"CG_Harv":0,"SBG_Harv":0,"WFG_Harv":4,"Watfowl_Harv":147,"Num_Hunters":197,"Birds_Per_Hunt":0.75,"Ducks_Per_Hunt":0.73,"Blind_Vac":1,"Wade_Vac":5,"Total_Pos":84,"PL_Avail":74,"PL_Draw":96,"Comments":null,"Area_ID":5001},{"RecId":3484,"Area":"Duck Creek CA","Season":"2019-2020","Week":9,"Report_Date":"2020-01-05T00:00:00","Duck_Pop":15098,"Goose_Pop":null,"Duck_Harv":134,"CG_Harv":0,"SBG_Harv":0,"WFG_Harv":0,"Watfowl_Harv":134,"Num_Hunters":143,"Birds_Per_Hunt":0.94,"Ducks_Per_Hunt":0.94,"Blind_Vac":6,"Wade_Vac":15,"Total_Pos":84,"PL_Avail":76,"PL_Draw":60,"Comments":null,"Area_ID":5001},{"RecId":3518,"Area":"Duck Creek CA","Season":"2019-2020","Week":10,"Report_Date":"2020-01-06T00:00:00","Duck_Pop":10869,"Goose_Pop":null,"Duck_Harv":81,"CG_Harv":0,"SBG_Harv":0,"WFG_Harv":0,"Watfowl_Harv":81,"Num_Hunters":87,"Birds_Per_Hunt":0.93,"Ducks_Per_Hunt":0.93,"Blind_Vac":7,"Wade_Vac":18,"Total_Pos":66,"PL_Avail":55,"PL_Draw":36,"Comments":null,"Area_ID":5001},{"RecId":3519,"Area":"Duck Creek CA","Season":"2019-2020","Week":10,"Report_Date":"2020-01-07T00:00:00","Duck_Pop":10869,"Goose_Pop":null,"Duck_Harv":115,"CG_Harv":0,"SBG_Harv":0,"WFG_Harv":1,"Watfowl_Harv":116,"Num_Hunters":96,"Birds_Per_Hunt":1.21,"Ducks_Per_Hunt":1.20,"Blind_Vac":10,"Wade_Vac":16,"Total_Pos":73,"PL_Avail":67,"PL_Draw":41,"Comments":null,"Area_ID":5001},{"RecId":3520,"Area":"Duck Creek CA","Season":"2019-2020","Week":10,"Report_Date":"2020-01-08T00:00:00","Duck_Pop":10869,"Goose_Pop":null,"Duck_Harv":71,"CG_Harv":0,"SBG_Harv":0,"WFG_Harv":0,"Watfowl_Harv":71,"Num_Hunters":75,"Birds_Per_Hunt":0.95,"Ducks_Per_Hunt":0.95,"Blind_Vac":10,"Wade_Vac":21,"Total_Pos":67,"PL_Avail":61,"PL_Draw":32,"Comments":null,"Area_ID":5001},{"RecId":3539,"Area":"Duck Creek CA","Season":"2019-2020","Week":10,"Report_Date":"2020-01-09T00:00:00","Duck_Pop":10869,"Goose_Pop":null,"Duck_Harv":62,"CG_Harv":0,"SBG_Harv":0,"WFG_Harv":1,"Watfowl_Harv":63,"Num_Hunters":75,"Birds_Per_Hunt":0.84,"Ducks_Per_Hunt":0.83,"Blind_Vac":16,"Wade_Vac":10,"Total_Pos":62,"PL_Avail":56,"PL_Draw":31,"Comments":null,"Area_ID":5001},{"RecId":3540,"Area":"Duck Creek CA","Season":"2019-2020","Week":10,"Report_Date":"2020-01-10T00:00:00","Duck_Pop":10869,"Goose_Pop":null,"Duck_Harv":69,"CG_Harv":0,"SBG_Harv":0,"WFG_Harv":0,"Watfowl_Harv":69,"Num_Hunters":48,"Birds_Per_Hunt":1.44,"Ducks_Per_Hunt":1.44,"Blind_Vac":12,"Wade_Vac":18,"Total_Pos":55,"PL_Avail":51,"PL_Draw":22,"Comments":null,"Area_ID":5001},{"RecId":3541,"Area":"Duck Creek CA","Season":"2019-2020","Week":10,"Report_Date":"2020-01-11T00:00:00","Duck_Pop":10869,"Goose_Pop":null,"Duck_Harv":90,"CG_Harv":0,"SBG_Harv":0,"WFG_Harv":0,"Watfowl_Harv":90,"Num_Hunters":90,"Birds_Per_Hunt":1.00,"Ducks_Per_Hunt":1.00,"Blind_Vac":8,"Wade_Vac":16,"Total_Pos":57,"PL_Avail":50,"PL_Draw":27,"Comments":null,"Area_ID":5001},{"RecId":3542,"Area":"Duck Creek CA","Season":"2019-2020","Week":10,"Report_Date":"2020-01-12T00:00:00","Duck_Pop":10869,"Goose_Pop":null,"Duck_Harv":106,"CG_Harv":1,"SBG_Harv":0,"WFG_Harv":0,"Watfowl_Harv":107,"Num_Hunters":141,"Birds_Per_Hunt":0.76,"Ducks_Per_Hunt":0.75,"Blind_Vac":0,"Wade_Vac":1,"Total_Pos":65,"PL_Avail":57,"PL_Draw":62,"Comments":null,"Area_ID":5001}]}